PyFileLock/__init__.py
PyFileLock/__main__.py
PyFileLock-1.0.2.dist-info/LICENSE
PyFileLock-1.0.2.dist-info/METADATA
PyFileLock-1.0.2.dist-info/WHEEL
PyFileLock-1.0.2.dist-info/top_level.txt
PyFileLock-1.0.2.dist-info/RECORD
