Metadata-Version: 2.1
Name: PyFileLock
Version: 1.0.2
Summary: Python dosyalarını 15 farklı kombinasyonda şifreler.
Home-page: https://github.com/aylak-github/PyFileLock
Author: aylak-github
License: GNU AFFERO GENERAL PUBLIC LICENSE (v3)
Classifier: Programming Language :: Python :: 3
Classifier: Programming Language :: Python :: 3.8
Classifier: Programming Language :: Python :: 3.9
Classifier: Programming Language :: Python :: 3.10
Classifier: License :: OSI Approved :: GNU General Public License v3 (GPLv3)
Classifier: Operating System :: OS Independent
Requires-Python: >3
License-File: LICENSE
Requires-Dist: rich
